calculadoraFasesLunares/__init__.py
calculadoraFasesLunares/faselunar.py
calculadorafaselunar-0.1.1.dist-info/METADATA
calculadorafaselunar-0.1.1.dist-info/WHEEL
calculadorafaselunar-0.1.1.dist-info/top_level.txt
calculadorafaselunar-0.1.1.dist-info/RECORD
