Metadata-Version: 2.1
Name: calculadorafaselunar
Version: 0.1.1
Summary: Librería demo
Home-page: 
Author: Sol troncoso
Author-email: sol.troncoso@usach.cl
License: MIT
Classifier: Intended Audience :: Developers
Classifier: License :: OSI Approved :: MIT License
Classifier: Programming Language :: Python
Classifier: Programming Language :: Python :: 3
Classifier: Programming Language :: Python :: 3.6
Classifier: Programming Language :: Python :: 3.7
Classifier: Programming Language :: Python :: 3.8
Classifier: Programming Language :: Python :: 3.9
Classifier: Operating System :: OS Independent
Requires-Dist: emoji
